apbf/__init__.py
apbf/apbf_s3.py
python_persistent_apbf-0.2.0.dist-info/METADATA
python_persistent_apbf-0.2.0.dist-info/WHEEL
python_persistent_apbf-0.2.0.dist-info/RECORD
